{
  "project_info": {
    "project_number": "157302910991",
    "firebase_url": "https://bookrecognition-90f0e.firebaseio.com",
    "project_id": "bookrecognition-90f0e",
    "storage_bucket": "bookrecognition-90f0e.appspot.com"
  },
  "client": [
    {
      "client_info": {
        "mobilesdk_app_id": "1:157302910991:android:e552c859429e6166b3737a",
        "android_client_info": {
          "package_name": "com.google.firebase.codelab.mlkit"
        }
      },
      "oauth_client": [
        {
          "client_id": "157302910991-sbv64dra2mjj3ktfda7q25iuoqj5rka7.apps.googleusercontent.com",
          "client_type": 3
        }
      ],
      "api_key": [
        {
          "current_key": "AIzaSyBD_DGVGhSObd3hvwpaQXCoC5lLKSg0-zI"
        }
      ],
      "services": {
        "appinvite_service": {
          "other_platform_oauth_client": [
            {
              "client_id": "157302910991-sbv64dra2mjj3ktfda7q25iuoqj5rka7.apps.googleusercontent.com",
              "client_type": 3
            }
          ]
        }
      }
    }
  ],
  "configuration_version": "1"
}